setup.py
djorm_ext_pggeom.egg-info/PKG-INFO
djorm_ext_pggeom.egg-info/SOURCES.txt
djorm_ext_pggeom.egg-info/dependency_links.txt
djorm_ext_pggeom.egg-info/requires.txt
djorm_ext_pggeom.egg-info/top_level.txt
djorm_pggeom/__init__.py
djorm_pggeom/adapt.py
djorm_pggeom/expressions.py
djorm_pggeom/fields.py
djorm_pggeom/functions.py
djorm_pggeom/models.py
djorm_pggeom/objects.py