Metadata-Version: 1.1
Name: djorm-ext-pggeom
Version: 0.4.1
Summary: PostgreSQL native geometric types and fields  extension for Django.
Home-page: https://github.com/niwibe/djorm-ext-pggeom
Author: Andrey Antukh
Author-email: niwi@niwi.be
License: BSD
Platform: OS Independent
Classifier: Development Status :: 4 - Beta
Classifier: Framework :: Django
Classifier: Intended Audience :: Developers
Classifier: License :: OSI Approved :: BSD License
Classifier: Operating System :: OS Independent
Classifier: Programming Language :: Python
Classifier: Topic :: Internet :: WWW/HTTP
